cancerdata_pii/__init__.py
cancerdata_pii/hi.py
cancerdata_pii-0.1.4.dist-info/METADATA
cancerdata_pii-0.1.4.dist-info/WHEEL
cancerdata_pii-0.1.4.dist-info/licenses/LICENSE
cancerdata_pii-0.1.4.dist-info/RECORD
